polimorfo/__init__.py
polimorfo/cli.py
polimorfo/polimorfo.py
polimorfo/datasets/__init__.py
polimorfo/datasets/coco.py
polimorfo/datasets/instancecoco.py
polimorfo/datasets/semanticcoco.py
polimorfo/datasets/splitter.py
polimorfo/utils/__init__.py
polimorfo/utils/maskutils.py
polimorfo/utils/mergeutils.py
polimorfo/utils/visualizeutils.py
polimorfo-0.10.35.dist-info/AUTHORS.rst
polimorfo-0.10.35.dist-info/LICENSE
polimorfo-0.10.35.dist-info/METADATA
polimorfo-0.10.35.dist-info/WHEEL
polimorfo-0.10.35.dist-info/entry_points.txt
polimorfo-0.10.35.dist-info/top_level.txt
polimorfo-0.10.35.dist-info/RECORD
