Metadata-Version: 2.1
Name: polimorfo
Version: 0.10.35
Summary: a dataset loader and converter for object detection segmentation and classification
Home-page: https://github.com/fabiofumarola/polimorfo
Author: Fabio Fumarola
Author-email: fabiofumarola@gmail.com
License: Apache Software License 2.0
Keywords: polimorfo
Platform: UNKNOWN
Classifier: Development Status :: 2 - Pre-Alpha
Classifier: Intended Audience :: Developers
Classifier: License :: OSI Approved :: Apache Software License
Classifier: Natural Language :: English
Classifier: Programming Language :: Python :: 3.8
Classifier: Programming Language :: Python :: 3.9
Requires-Python: >=3.6
License-File: LICENSE
License-File: AUTHORS.rst
Requires-Dist: tqdm (>=4.62.3)
Requires-Dist: numpy (>=1.22.2)
Requires-Dist: pycocotools (>=2.0.4)
Requires-Dist: Pillow (>=5.3.0)
Requires-Dist: matplotlib (>=3.4.3)
Requires-Dist: opencv-python-headless (>=4.6.0.66)
Requires-Dist: Deprecated (>=1.2.13)
Requires-Dist: scikit-multilearn (>=0.2.0)
Requires-Dist: scikit-image (>=0.19.2)
Requires-Dist: scipy (>=1.8.0)
Requires-Dist: scikit-learn (>=1.0.2)
Requires-Dist: rich (>=12.0.0)
